_mjx.cpython-37m-darwin.so
libgrpc_csharp_ext.18.0.0.dylib
libgrpc_csharp_ext.18.dylib
libgrpc_csharp_ext.dylib
libz.1.2.11.dylib
libz.1.dylib
libz.dylib
mjx/__init__.py
mjx/action.py
mjx/agents.py
mjx/const.py
mjx/env.py
mjx/event.py
mjx/hand.py
mjx/observation.py
mjx/open.py
mjx/state.py
mjx/tile.py
mjx/utils.py
mjx/visualizer/1000.svg
mjx/visualizer/1000_mini.svg
mjx/visualizer/100_mini.svg
mjx/visualizer/GL-MahjongTile.ttf
mjx/visualizer/__init__.py
mjx/visualizer/converter.py
mjx/visualizer/selector.py
mjx/visualizer/svg.py
mjx/visualizer/visualizer.py
mjxproto/__init__.py
mjxproto/mjx_pb2.py
mjxproto/mjx_pb2_grpc.py
tests_py/__init__.py
tests_py/_test_cli_selector.py
tests_py/test_action.py
tests_py/test_agents.py
tests_py/test_env.py
tests_py/test_event.py
tests_py/test_features.py
tests_py/test_hand.py
tests_py/test_observation.py
tests_py/test_state.py
tests_py/test_svgwrite.py
tests_py/test_tile.py
tests_py/test_visualizer.py
mjx-0.1.0.dist-info/LICENSE
mjx-0.1.0.dist-info/METADATA
mjx-0.1.0.dist-info/WHEEL
mjx-0.1.0.dist-info/top_level.txt
mjx-0.1.0.dist-info/RECORD
