Metadata-Version: 2.1
Name: mjx
Version: 0.1.0
Author: Mjx Project Team
Author-email: koyamada-s@sys.i.kyoto-u.ac.jp
License-File: LICENSE
Requires-Dist: google (==3.0.0)
Requires-Dist: protobuf (==3.17.3)
Requires-Dist: grpcio (==1.39.0)
Requires-Dist: numpy
Requires-Dist: pillow
Requires-Dist: svgwrite
Requires-Dist: inquirer
Provides-Extra: test
Requires-Dist: pytest ; extra == 'test'
